odoo/addons/pos_meal_voucher/README.rst
odoo/addons/pos_meal_voucher/__init__.py
odoo/addons/pos_meal_voucher/__manifest__.py
odoo/addons/pos_meal_voucher/data/barcode_rule.xml
odoo/addons/pos_meal_voucher/demo/product_category.xml
odoo/addons/pos_meal_voucher/demo/product_product.xml
odoo/addons/pos_meal_voucher/i18n/fr.po
odoo/addons/pos_meal_voucher/i18n/it.po
odoo/addons/pos_meal_voucher/i18n/pos_meal_voucher.pot
odoo/addons/pos_meal_voucher/models/__init__.py
odoo/addons/pos_meal_voucher/models/account_journal.py
odoo/addons/pos_meal_voucher/models/barcode_rule.py
odoo/addons/pos_meal_voucher/models/pos_config.py
odoo/addons/pos_meal_voucher/models/pos_order.py
odoo/addons/pos_meal_voucher/models/product_category.py
odoo/addons/pos_meal_voucher/models/product_product.py
odoo/addons/pos_meal_voucher/models/product_template.py
odoo/addons/pos_meal_voucher/readme/CONFIGURE.rst
odoo/addons/pos_meal_voucher/readme/CONTRIBUTORS.rst
odoo/addons/pos_meal_voucher/readme/CREDITS.rst
odoo/addons/pos_meal_voucher/readme/DESCRIPTION.rst
odoo/addons/pos_meal_voucher/readme/ROADMAP.rst
odoo/addons/pos_meal_voucher/readme/USAGE.rst
odoo/addons/pos_meal_voucher/static/description/account_journal_form.png
odoo/addons/pos_meal_voucher/static/description/front_ui_pos_order_screen.png
odoo/addons/pos_meal_voucher/static/description/front_ui_pos_payment_screen.png
odoo/addons/pos_meal_voucher/static/description/front_ui_pos_payment_screen_summary.png
odoo/addons/pos_meal_voucher/static/description/front_ui_pos_payment_screen_warning.png
odoo/addons/pos_meal_voucher/static/description/icon.png
odoo/addons/pos_meal_voucher/static/description/index.html
odoo/addons/pos_meal_voucher/static/description/issuer_1_up_dejeuner.jpg
odoo/addons/pos_meal_voucher/static/description/issuer_2_ticket_restaurant.jpeg
odoo/addons/pos_meal_voucher/static/description/issuer_3_apetiz.png
odoo/addons/pos_meal_voucher/static/description/issuer_4_pass_restaurant.png
odoo12_addon_pos_meal_voucher-12.0.1.0.8.dist-info/METADATA
odoo12_addon_pos_meal_voucher-12.0.1.0.8.dist-info/WHEEL
odoo12_addon_pos_meal_voucher-12.0.1.0.8.dist-info/top_level.txt
odoo12_addon_pos_meal_voucher-12.0.1.0.8.dist-info/RECORD
